imagemounter_mitre/__init__.py
imagemounter_mitre/_util.py
imagemounter_mitre/dependencies.py
imagemounter_mitre/disk.py
imagemounter_mitre/exceptions.py
imagemounter_mitre/filesystems.py
imagemounter_mitre/parser.py
imagemounter_mitre/unmounter.py
imagemounter_mitre/volume.py
imagemounter_mitre/volume_system.py
imagemounter_mitre/cli/__init__.py
imagemounter_mitre/cli/imount.py
imagemounter_mitre/cli/shell.py
imagemounter_mitre-2025.2.27.dist-info/LICENSE
imagemounter_mitre-2025.2.27.dist-info/METADATA
imagemounter_mitre-2025.2.27.dist-info/WHEEL
imagemounter_mitre-2025.2.27.dist-info/entry_points.txt
imagemounter_mitre-2025.2.27.dist-info/top_level.txt
imagemounter_mitre-2025.2.27.dist-info/RECORD
