Metadata-Version: 2.1
Name: imagemounter-mitre
Version: 2025.2.27
Summary: Command line utility and Python package to ease the (un)mounting of forensic disk images.
Home-page: https://github.com/mitre/imagemounter
Author: The MITRE Corporation
License: MIT
Keywords: encase,aff,dd,disk image,ewfmount,affuse,xmount,imount
Classifier: Development Status :: 5 - Production/Stable
Classifier: Environment :: Console
Classifier: Intended Audience :: Developers
Classifier: Intended Audience :: Legal Industry
Classifier: Intended Audience :: System Administrators
Classifier: License :: OSI Approved :: MIT License
Classifier: Operating System :: POSIX :: Linux
Classifier: Programming Language :: Python :: 3.6
Classifier: Programming Language :: Python :: 3.7
Classifier: Programming Language :: Python :: 3.8
Classifier: Programming Language :: Python :: 3.9
Classifier: Programming Language :: Python :: 3.10
Classifier: Topic :: Scientific/Engineering :: Information Analysis
Classifier: Topic :: System :: Filesystems
Classifier: Topic :: Terminals
Classifier: Topic :: Utilities
License-File: LICENSE
Requires-Dist: termcolor >=1.0.0
